Abhay_STT/__init__.py
AbhaySTT-0.2.dist-info/METADATA
AbhaySTT-0.2.dist-info/WHEEL
AbhaySTT-0.2.dist-info/top_level.txt
AbhaySTT-0.2.dist-info/RECORD
