Metadata-Version: 2.1
Name: AbhaySTT
Version: 0.2
Summary: This is the awesome speech to text package created by Me(Abhay Agnihori)
Author: Abhay Agnihotri
Author-email: abhayagnihotri976@gmail.com
